deslackify/__init__.py
deslackify-0.5.0.dist-info/LICENSE.txt
deslackify-0.5.0.dist-info/METADATA
deslackify-0.5.0.dist-info/WHEEL
deslackify-0.5.0.dist-info/entry_points.txt
deslackify-0.5.0.dist-info/top_level.txt
deslackify-0.5.0.dist-info/RECORD
