Metadata-Version: 2.1
Name: deslackify
Version: 0.5.0
Summary: A program to delete old slack messages.
Home-page: https://github.com/bboe/deslackify
Author: Bryce Boe
Author-email: bbzbryce@gmail.com
License: Simplified BSD License
Keywords: slack
Platform: UNKNOWN
Classifier: Intended Audience :: Developers
Classifier: License :: OSI Approved :: BSD License
Classifier: Programming Language :: Python
Classifier: Programming Language :: Python :: 3
Requires-Dist: slacker (<0.13,>=0.12)
